bookbaker/__init__.py
bookbaker/__main__.py
bookbaker/classes.py
bookbaker/cli.py
bookbaker/config.py
bookbaker/exc.py
bookbaker/misc.py
bookbaker/roles/__init__.py
bookbaker/roles/autocrawler.py
bookbaker/roles/base.py
bookbaker/roles/deepl.py
bookbaker/roles/epub.py
bookbaker/roles/esj.py
bookbaker/roles/gemini.py
bookbaker/roles/gpt.py
bookbaker/roles/kakuyomu.py
bookbaker/roles/masiro.py
bookbaker/roles/novelup.py
bookbaker/roles/syosetu_com.py
bookbaker/roles/syosetu_org.py
bookbaker/utils.py
bookbaker-0.1.16.dist-info/LICENSE
bookbaker-0.1.16.dist-info/METADATA
bookbaker-0.1.16.dist-info/WHEEL
bookbaker-0.1.16.dist-info/entry_points.txt
bookbaker-0.1.16.dist-info/RECORD
