Metadata-Version: 2.1
Name: bookbaker
Version: 0.1.16
Summary: Components for auto-translation of novel and manga.
Home-page: https://github.com/VermiIIi0n/bookbaker
License: MIT
Keywords: utilities,translation,automation,novel,webnovel,lightnovel
Author: VermiIIi0n
Author-email: dungeon.behind0t@icloud.com
Requires-Python: >=3.12,<4.0
Classifier: Development Status :: 4 - Beta
Classifier: Framework :: Pytest
Classifier: Intended Audience :: Developers
Classifier: License :: OSI Approved :: MIT License
Classifier: Operating System :: OS Independent
Classifier: Programming Language :: Python :: 3
Classifier: Programming Language :: Python :: 3.12
Classifier: Programming Language :: Python :: Implementation :: CPython
Classifier: Programming Language :: Python :: Implementation :: PyPy
Classifier: Topic :: Utilities
Classifier: Typing :: Typed
Requires-Dist: aiodeepl (>=0.1.4,<0.2.0)
Requires-Dist: async-tinydb (>=1.7.1,<2.0.0)
Requires-Dist: beautifulsoup4 (>=4.12.3,<5.0.0)
Requires-Dist: ebooklib (>=0.18,<0.19)
Requires-Dist: gemnine (>=0.1.11,<0.2.0)
Requires-Dist: h2 (>=4.1.0,<5.0.0)
Requires-Dist: httpx[http2,socks] (>=0.26.0)
Requires-Dist: lxml (>=5.1.0,<6.0.0)
Requires-Dist: ngptbot (>=0.3.5,<0.4.0)
Requires-Dist: pillow (>=10.2.0,<11.0.0)
Requires-Dist: pydantic (>=2.6.1,<3.0.0)
Requires-Dist: ujson (>=5.9.0,<6.0.0)
Requires-Dist: vermils (>=0.3.6,<0.4.0)
Project-URL: Issues, https://github.com/VermiIIi0n/bookbaker/issues
